LICENSE.txt
README.rst
setup.py
ox_secrets/__init__.py
ox_secrets/server.py
ox_secrets/settings.py
ox_secrets.egg-info/PKG-INFO
ox_secrets.egg-info/SOURCES.txt
ox_secrets.egg-info/dependency_links.txt
ox_secrets.egg-info/entry_points.txt
ox_secrets.egg-info/requires.txt
ox_secrets.egg-info/top_level.txt
ox_secrets/core/__init__.py
ox_secrets/core/aws.py
ox_secrets/core/common.py
ox_secrets/core/evs.py
ox_secrets/core/fss.py
ox_secrets/ui/__init__.py
ox_secrets/ui/cli.py